npit/__init__.py
npit/example.py
npit-0.0.1.dist-info/METADATA
npit-0.0.1.dist-info/WHEEL
npit-0.0.1.dist-info/licenses/LICENSE
npit-0.0.1.dist-info/RECORD
