Metadata-Version: 2.4
Name: npit
Version: 0.0.1
Summary: I !love python
Author-email: Arthur <bguarthur@gamil.com>
License-Expression: MIT
License-File: LICENSE
Classifier: Operating System :: OS Independent
Classifier: Programming Language :: Python :: 3
Requires-Python: >=3.9
